autobiasdetector/BiasInductionEngine.py
autobiasdetector/CEPExtractEngine.py
autobiasdetector/ClusterEngine.py
autobiasdetector/Inference.py
autobiasdetector/__init__.py
autobiasdetector/config.py
autobiasdetector/dataload.py
autobiasdetector-0.0.2.data/data/requirements.txt
autobiasdetector-0.0.2.dist-info/METADATA
autobiasdetector-0.0.2.dist-info/WHEEL
autobiasdetector-0.0.2.dist-info/top_level.txt
autobiasdetector-0.0.2.dist-info/RECORD
