Metadata-Version: 2.1
Name: autobiasdetector
Version: 0.0.2
Summary: tools for detecting bias patterns of LLMs
Home-page: https://pypi.org/project/autobiasdetector/
Author: Zhouhao Sun
Author-email: zhsun@ir.hit.edu.cn
Classifier: Programming Language :: Python :: 3
Classifier: License :: OSI Approved :: MIT License
Classifier: Operating System :: OS Independent
Requires-Python: >=3.10
Requires-Dist: accelerate ==0.30.0
Requires-Dist: aiofiles ==23.2.1
Requires-Dist: aiohttp ==3.9.5
Requires-Dist: aioprometheus ==23.12.0
Requires-Dist: aiosignal ==1.3.1
Requires-Dist: altair ==5.3.0
Requires-Dist: annotated-types ==0.6.0
Requires-Dist: anyio ==3.7.1
Requires-Dist: async-timeout ==4.0.3
Requires-Dist: attrs ==23.2.0
Requires-Dist: backports.tarfile ==1.1.1
Requires-Dist: beautifulsoup4 ==4.12.3
Requires-Dist: bs4 ==0.0.2
Requires-Dist: certifi ==2024.2.2
Requires-Dist: cffi ==1.16.0
Requires-Dist: charset-normalizer ==3.3.2
Requires-Dist: click ==8.1.7
Requires-Dist: cloudpickle ==3.0.0
Requires-Dist: cmake ==3.29.2
Requires-Dist: contourpy ==1.2.1
Requires-Dist: cryptography ==42.0.6
Requires-Dist: cycler ==0.12.1
Requires-Dist: datasets ==2.19.1
Requires-Dist: deepspeed ==0.14.2
Requires-Dist: dill ==0.3.8
Requires-Dist: diskcache ==5.6.3
Requires-Dist: distro ==1.9.0
Requires-Dist: dnspython ==2.6.1
Requires-Dist: docutils ==0.21.2
Requires-Dist: email-validator ==2.1.1
Requires-Dist: exceptiongroup ==1.2.1
Requires-Dist: fastapi ==0.111.0
Requires-Dist: fastapi-cli ==0.0.2
Requires-Dist: ffmpy ==0.3.2
Requires-Dist: filelock ==3.14.0
Requires-Dist: fonttools ==4.51.0
Requires-Dist: frozenlist ==1.4.1
Requires-Dist: fschat ==0.2.36
Requires-Dist: fsspec ==2024.3.1
Requires-Dist: gradio ==4.29.0
Requires-Dist: gradio-client ==0.16.1
Requires-Dist: h11 ==0.14.0
Requires-Dist: hjson ==3.1.0
Requires-Dist: httpcore ==1.0.5
Requires-Dist: httptools ==0.6.1
Requires-Dist: httpx ==0.27.0
Requires-Dist: huggingface-hub ==0.23.0
Requires-Dist: idna ==3.7
Requires-Dist: importlib-metadata ==7.1.0
Requires-Dist: importlib-resources ==6.4.0
Requires-Dist: interegular ==0.3.3
Requires-Dist: jaraco.classes ==3.4.0
Requires-Dist: jaraco.context ==5.3.0
Requires-Dist: jaraco.functools ==4.0.1
Requires-Dist: jeepney ==0.8.0
Requires-Dist: Jinja2 ==3.1.4
Requires-Dist: joblib ==1.4.2
Requires-Dist: jsonschema ==4.22.0
Requires-Dist: jsonschema-specifications ==2023.12.1
Requires-Dist: keyring ==25.2.0
Requires-Dist: kiwisolver ==1.4.5
Requires-Dist: lark ==1.1.9
Requires-Dist: llvmlite ==0.42.0
Requires-Dist: lm-format-enforcer ==0.9.8
Requires-Dist: markdown-it-py ==3.0.0
Requires-Dist: markdown2 ==2.4.13
Requires-Dist: MarkupSafe ==2.1.5
Requires-Dist: matplotlib ==3.8.4
Requires-Dist: mdurl ==0.1.2
Requires-Dist: more-itertools ==10.2.0
Requires-Dist: mpmath ==1.3.0
Requires-Dist: msgpack ==1.0.8
Requires-Dist: multidict ==6.0.5
Requires-Dist: multiprocess ==0.70.16
Requires-Dist: nest-asyncio ==1.6.0
Requires-Dist: networkx ==3.3
Requires-Dist: nh3 ==0.2.17
Requires-Dist: ninja ==1.11.1.1
Requires-Dist: numba ==0.59.1
Requires-Dist: numpy ==1.26.4
Requires-Dist: nvidia-cublas-cu12 ==12.1.3.1
Requires-Dist: nvidia-cuda-cupti-cu12 ==12.1.105
Requires-Dist: nvidia-cuda-nvrtc-cu12 ==12.1.105
Requires-Dist: nvidia-cuda-runtime-cu12 ==12.1.105
Requires-Dist: nvidia-cudnn-cu12 ==8.9.2.26
Requires-Dist: nvidia-cufft-cu12 ==11.0.2.54
Requires-Dist: nvidia-curand-cu12 ==10.3.2.106
Requires-Dist: nvidia-cusolver-cu12 ==11.4.5.107
Requires-Dist: nvidia-cusparse-cu12 ==12.1.0.106
Requires-Dist: nvidia-ml-py ==12.550.52
Requires-Dist: nvidia-nccl-cu12 ==2.18.1
Requires-Dist: nvidia-nvjitlink-cu12 ==12.4.127
Requires-Dist: nvidia-nvtx-cu12 ==12.1.105
Requires-Dist: openai ==1.2.2
Requires-Dist: orjson ==3.10.3
Requires-Dist: outlines ==0.0.34
Requires-Dist: packaging ==24.0
Requires-Dist: pandas ==2.2.2
Requires-Dist: peft ==0.10.0
Requires-Dist: pillow ==10.3.0
Requires-Dist: pkginfo ==1.10.0
Requires-Dist: prometheus-fastapi-instrumentator ==7.0.0
Requires-Dist: prometheus-client ==0.20.0
Requires-Dist: prompt-toolkit ==3.0.43
Requires-Dist: protobuf ==5.26.1
Requires-Dist: psutil ==5.9.8
Requires-Dist: py-cpuinfo ==9.0.0
Requires-Dist: pyarrow ==16.0.0
Requires-Dist: pyarrow-hotfix ==0.6
Requires-Dist: pycparser ==2.22
Requires-Dist: pydantic ==2.7.1
Requires-Dist: pydantic-core ==2.18.2
Requires-Dist: pydub ==0.25.1
Requires-Dist: Pygments ==2.18.0
Requires-Dist: pynvml ==11.5.0
Requires-Dist: pyparsing ==3.1.2
Requires-Dist: python-dateutil ==2.9.0.post0
Requires-Dist: python-dotenv ==1.0.1
Requires-Dist: python-multipart ==0.0.9
Requires-Dist: pytz ==2024.1
Requires-Dist: PyYAML ==6.0.1
Requires-Dist: quantile-python ==1.1
Requires-Dist: ray ==2.20.0
Requires-Dist: readme-renderer ==43.0
Requires-Dist: referencing ==0.35.1
Requires-Dist: regex ==2024.4.28
Requires-Dist: requests ==2.31.0
Requires-Dist: requests-toolbelt ==1.0.0
Requires-Dist: rfc3986 ==2.0.0
Requires-Dist: rich ==13.7.1
Requires-Dist: rpds-py ==0.18.0
Requires-Dist: ruff ==0.4.3
Requires-Dist: safetensors ==0.4.3
Requires-Dist: scikit-learn ==1.2.2
Requires-Dist: scipy ==1.13.0
Requires-Dist: SecretStorage ==3.3.3
Requires-Dist: semantic-version ==2.10.0
Requires-Dist: sentencepiece ==0.2.0
Requires-Dist: shellingham ==1.5.4
Requires-Dist: shortuuid ==1.0.13
Requires-Dist: six ==1.16.0
Requires-Dist: sniffio ==1.3.1
Requires-Dist: soupsieve ==2.5
Requires-Dist: starlette ==0.37.2
Requires-Dist: svgwrite ==1.4.3
Requires-Dist: sympy ==1.12
Requires-Dist: threadpoolctl ==3.5.0
Requires-Dist: tiktoken ==0.6.0
Requires-Dist: timeout-decorator ==0.5.0
Requires-Dist: tokenizers ==0.15.2
Requires-Dist: tomlkit ==0.12.0
Requires-Dist: toolz ==0.12.1
Requires-Dist: torch ==2.1.2
Requires-Dist: tqdm ==4.66.4
Requires-Dist: transformers ==4.37.0
Requires-Dist: triton ==2.1.0
Requires-Dist: twine ==5.0.0
Requires-Dist: typer ==0.12.3
Requires-Dist: typing-extensions ==4.11.0
Requires-Dist: tzdata ==2024.1
Requires-Dist: ujson ==5.9.0
Requires-Dist: urllib3 ==2.2.1
Requires-Dist: uvicorn ==0.29.0
Requires-Dist: uvloop ==0.19.0
Requires-Dist: vllm ==0.3.0
Requires-Dist: vllm-nccl-cu12 ==2.18.1.0.4.0
Requires-Dist: watchfiles ==0.21.0
Requires-Dist: wavedrom ==2.0.3.post3
Requires-Dist: wcwidth ==0.2.13
Requires-Dist: websockets ==11.0.3
Requires-Dist: xformers ==0.0.23.post1
Requires-Dist: xxhash ==3.4.1
Requires-Dist: yarl ==1.9.4
Requires-Dist: zipp ==3.18.1
